{
  "BUGZILLA_URL": "https://bugzilla.mozilla.org/buglist.cgi",
  "BUGZILLA_REST_URL": "https://bugzilla.mozilla.org/rest/bug",
  "bugQueries": [
    {
      "id": "UpliftsBeta",
      "url": "?o1=substring&f1=flagtypes.name&v1=approval-mozilla-beta%3F"
    },
    {
      "id": "UpliftsRelease",
      "url": "?o1=substring&f1=flagtypes.name&v1=approval-mozilla-release%3F"
    },
    {
      "id": "UpliftsESR",
      "url": "?o1=substring&f1=flagtypes.name&v1=approval-mozilla-esr102%3F"
    }
  ],
  "refreshMinutes": 30
}
